{
  "root": {
    "id": {
      "id": "alive/themedcard",
      "parentId": "alive",
      "type": "Class",
      "modifiers": [
        "public",
        "partial"
      ]
    },
    "uri": {
      "idUri": "alive/themedcard",
      "href": "alive/themedcard"
    },
    "titles": {
      "indexTitle": "ThemedCard",
      "fullyQualifiedIndexTitle": "Alive.ThemedCard"
    }
  },
  "descendants": [
    {
      "id": {
        "id": "alive/card",
        "parentId": "alive",
        "type": "Class",
        "modifiers": [
          "public",
          "partial"
        ]
      },
      "uri": {
        "idUri": "alive/card",
        "href": "alive/card"
      },
      "titles": {
        "indexTitle": "Card",
        "fullyQualifiedIndexTitle": "Alive.Card"
      }
    }
  ]
}